llama_index/cli/__init__.py
llama_index/cli/command_line.py
llama_index/cli/new_package/__init__.py
llama_index/cli/new_package/base.py
llama_index/cli/new_package/common/.gitignore
llama_index/cli/new_package/common/Makefile
llama_index/cli/new_package/common/_build
llama_index/cli/new_package/templates/__init__.py
llama_index/cli/new_package/templates/init.py
llama_index/cli/new_package/templates/pyproject.py
llama_index/cli/new_package/templates/readme.py
llama_index/cli/rag/__init__.py
llama_index/cli/rag/base.py
llama_index/cli/upgrade/__init__.py
llama_index/cli/upgrade/base.py
llama_index/cli/upgrade/mappings.json
llama_index_cli-0.5.2.dist-info/METADATA
llama_index_cli-0.5.2.dist-info/WHEEL
llama_index_cli-0.5.2.dist-info/entry_points.txt
llama_index_cli-0.5.2.dist-info/licenses/LICENSE
llama_index_cli-0.5.2.dist-info/RECORD
